odoo10_addon_slow_statement_logger-10.0.1.0.1.99.dev3-py3.8-nspkg.pth
odoo/addons/slow_statement_logger/README.rst
odoo/addons/slow_statement_logger/__init__.py
odoo/addons/slow_statement_logger/__manifest__.py
odoo/addons/slow_statement_logger/i18n/slow_statement_logger.pot
odoo/addons/slow_statement_logger/readme/CONTRIBUTORS.rst
odoo/addons/slow_statement_logger/readme/DESCRIPTION.rst
odoo/addons/slow_statement_logger/readme/USAGE.rst
odoo/addons/slow_statement_logger/static/description/icon.png
odoo/addons/slow_statement_logger/static/description/index.html
odoo10_addon_slow_statement_logger-10.0.1.0.1.99.dev3.dist-info/METADATA
odoo10_addon_slow_statement_logger-10.0.1.0.1.99.dev3.dist-info/WHEEL
odoo10_addon_slow_statement_logger-10.0.1.0.1.99.dev3.dist-info/namespace_packages.txt
odoo10_addon_slow_statement_logger-10.0.1.0.1.99.dev3.dist-info/top_level.txt
odoo10_addon_slow_statement_logger-10.0.1.0.1.99.dev3.dist-info/RECORD
